django_thread/__init__.py
django_thread-0.0.1.dist-info/LICENSE
django_thread-0.0.1.dist-info/METADATA
django_thread-0.0.1.dist-info/WHEEL
django_thread-0.0.1.dist-info/top_level.txt
django_thread-0.0.1.dist-info/RECORD
