Metadata-Version: 2.1
Name: django_thread
Version: 0.0.1
Summary: ## Helpers for using Django from threads
Home-page: https://github.com/ross/django-thread
Author: Ross McFaland
Author-email: rwmcfa1@gmail.com
License: MIT
Platform: UNKNOWN
Requires-Python: >=3.6
License-File: LICENSE
